kai/__init__.py
kai/extractors.py
kai/kai.py
kai/_version.py
kai-0.0.7.dist-info/top_level.txt
kai-0.0.7.dist-info/entry_points.txt
kai-0.0.7.dist-info/METADATA
kai-0.0.7.dist-info/DESCRIPTION.rst
kai-0.0.7.dist-info/metadata.json
kai-0.0.7.dist-info/WHEEL
kai-0.0.7.dist-info/RECORD
