Metadata-Version: 2.0
Name: kai
Version: 0.0.7
Summary: A Python package that gives you the power to extract any compressed file using the same simple syntax.
Home-page: http://github.com/brian-bates/kai
Author: Brian Bates
Author-email: brian@eccentricprototypes.com
License: UNKNOWN
Platform: UNKNOWN
Requires-Dist: rarfile
Requires-Dist: six
